<?xml version="1.0"?>
<opencv_storage>
<xml_kind>ルックアップテーブル</xml_kind>
<name>等高線2</name>
<description>輝度の等高線を描く。グレースケール画像で使用。カラー画像では意味不明になる</description>
<lut type_id="opencv-matrix">
  <rows>256</rows>
  <cols>1</cols>
  <dt>u</dt>
  <data>
    0 0 0 0 0 0 0 0 0 0 255 255 255 0 0 0 0 0 0 0 0 0 0 0 0 0 0 0 0 0
    255 255 255 0 0 0 0 0 0 0 0 0 0 0 0 0 0 0 0 0 255 255 255 0 0 0 0 0
    0 0 0 0 0 0 0 0 0 0 0 0 255 255 255 0 0 0 0 0 0 0 0 0 0 0 0 0 0 0 0
    0 255 255 255 0 0 0 0 0 0 0 0 0 0 0 0 0 0 0 0 0 255 255 255 0 0 0 0
    0 0 0 0 0 0 0 0 0 0 0 0 0 255 255 255 0 0 0 0 0 0 0 0 0 0 0 0 0 0 0
    0 0 255 255 255 0 0 0 0 0 0 0 0 0 0 0 0 0 0 0 0 0 255 255 255 0 0 0
    0 0 0 0 0 0 0 0 0 0 0 0 0 0 255 255 255 0 0 0 0 0 0 0 0 0 0 0 0 0 0
    0 0 0 255 255 255 0 0 0 0 0 0 0 0 0 0 0 0 0 0 0 0 0 255 255 255 0 0
    0 0 0 0 0 0 0 0 0 0 0 0 0 0 0 255 255 255 0 0 0</data></lut>
</opencv_storage>
